{
    "Bind": {
        "map_id": 0,
        "src": "./img/bind.png",
        "lineups" : [
            {
                "id" : 0,
                "type": "Recon",
                "target": "Attack",
                "charge": 1,
                "bounce": 0,
                "waypoints" : {
                    "stand": [0.39, 0.5],
                    "land": [0.55, 0.26]
                },
                "position" : {"src": "./img/lineups/position.png", "points": [0.3, 0.4, "red"], "lines": [0.3, 0.6, 0.4, 0.8, "blue"]},
                "lineup" : {"src": "./img/lineups/lineup.png", "points": [0.3, 0.4, "red"], "lines": [0.3, 0.6, 0.4, 0.8, "blue"]}
            },
            {
                "id" : 1,
                "type": "Recon",
                "target": "Attack",
                "charge": 2,
                "bounce": 2,
                "waypoints" : {
                    "stand": [0.48, 0.61],
                    "land": [0.79, 0.78]
                },
                "position" : {"src": "./img/lineups/position.png", "points": [0.3, 0.4, "red"], "lines": [0.3, 0.6, 0.4, 0.8, "blue"]},
                "lineup" : {"src": "./img/lineups/lineup.png", "points": [0.3, 0.4, "red"], "lines": [0.3, 0.6, 0.4, 0.8, "blue"]}
            }
        ]
    }
}